linkcheck_action/__init__.py
linkcheck_action/_nbdev.py
linkcheck_action/action.py
linkcheck_action-0.0.8.dist-info/METADATA
linkcheck_action-0.0.8.dist-info/WHEEL
linkcheck_action-0.0.8.dist-info/entry_points.txt
linkcheck_action-0.0.8.dist-info/top_level.txt
linkcheck_action-0.0.8.dist-info/RECORD
